nonebot_plugin_saa/__init__.py
nonebot_plugin_saa/abstract_factories.py
nonebot_plugin_saa/adapters/__init__.py
nonebot_plugin_saa/adapters/discord.py
nonebot_plugin_saa/adapters/dodo.py
nonebot_plugin_saa/adapters/feishu.py
nonebot_plugin_saa/adapters/kaiheila.py
nonebot_plugin_saa/adapters/onebot_v11.py
nonebot_plugin_saa/adapters/onebot_v12.py
nonebot_plugin_saa/adapters/qq.py
nonebot_plugin_saa/adapters/red.py
nonebot_plugin_saa/adapters/satori.py
nonebot_plugin_saa/adapters/telegram.py
nonebot_plugin_saa/auto_select_bot.py
nonebot_plugin_saa/config.py
nonebot_plugin_saa/registries/__init__.py
nonebot_plugin_saa/registries/message_id.py
nonebot_plugin_saa/registries/meta.py
nonebot_plugin_saa/registries/platform_send_target.py
nonebot_plugin_saa/registries/receipt.py
nonebot_plugin_saa/types/__init__.py
nonebot_plugin_saa/types/common_message_segment.py
nonebot_plugin_saa/types/custom_message_segment.py
nonebot_plugin_saa/utils/__init__.py
nonebot_plugin_saa/utils/const.py
nonebot_plugin_saa/utils/exceptions.py
nonebot_plugin_saa/utils/helpers.py
nonebot_plugin_send_anything_anywhere-0.7.1.dist-info/WHEEL
nonebot_plugin_send_anything_anywhere-0.7.1.dist-info/LICENSE
nonebot_plugin_send_anything_anywhere-0.7.1.dist-info/METADATA
nonebot_plugin_send_anything_anywhere-0.7.1.dist-info/RECORD
