Metadata-Version: 2.1
Name: nonebot-plugin-send-anything-anywhere
Version: 0.7.1
Summary: An adaptor for nonebot2 adaptors
License: MIT
Author: felinae98
Author-email: 731499577@qq.com
Requires-Python: >=3.9,<4.0
Classifier: Development Status :: 3 - Alpha
Classifier: License :: OSI Approved :: MIT License
Classifier: Operating System :: MacOS
Classifier: Operating System :: Microsoft :: Windows
Classifier: Operating System :: POSIX :: Linux
Classifier: Programming Language :: Python :: 3
Classifier: Programming Language :: Python :: 3.9
Classifier: Programming Language :: Python :: 3.10
Classifier: Programming Language :: Python :: 3.11
Classifier: Programming Language :: Python :: 3.10
Classifier: Programming Language :: Python :: 3.11
Classifier: Programming Language :: Python :: 3.12
Classifier: Programming Language :: Python :: 3.9
Requires-Dist: anyio (>=3.3.0,<5.0.0)
Requires-Dist: filetype (>=1.2.0,<2.0.0)
Requires-Dist: nonebot2 (>=2.3.0,<3.0.0)
Requires-Dist: pydantic (>=1.10.0,<3.0.0,!=2.5.0,!=2.5.1)
Requires-Dist: strenum (>=0.4.8,<0.5.0)
